README.md
setup.py
src/lightning_trainer/__init__.py
src/lightning_trainer/config.py
src/lightning_trainer/lightning.py
src/lightning_trainer/logger.py
src/lightning_trainer/parameters.py
src/lightning_trainer/system_info.py
src/lightning_trainer/trainer.py
src/lightning_trainer.egg-info/PKG-INFO
src/lightning_trainer.egg-info/SOURCES.txt
src/lightning_trainer.egg-info/dependency_links.txt
src/lightning_trainer.egg-info/entry_points.txt
src/lightning_trainer.egg-info/requires.txt
src/lightning_trainer.egg-info/top_level.txt